python_one_password/__init__.py
python_one_password/caching.py
python_one_password/cli.py
python_one_password/credentials.py
python_one_password/functions.py
python_one_password/skeleton.py
python_one_password/tags.py
python_one_password-0.1.1.dist-info/LICENSE.txt
python_one_password-0.1.1.dist-info/METADATA
python_one_password-0.1.1.dist-info/WHEEL
python_one_password-0.1.1.dist-info/entry_points.txt
python_one_password-0.1.1.dist-info/top_level.txt
python_one_password-0.1.1.dist-info/RECORD
