Metadata-Version: 2.1
Name: python-one-password
Version: 0.1.1
Summary: Imports metadata from 1Password vaults and allows for bulk manipulation of tags
Home-page: https://gerrit.linuxfoundation.org/infra/admin/repos/releng/python-one-password,general
Author: Matthew Watkins
Author-email: mwatkins@linuxfoundation.org
License: Apache-2.0
Project-URL: Source, https://github.com/lfit/releng-python-one-password
Project-URL: Documentation, https://github.com/lfit/releng-python-one-password#readme
Project-URL: Tracker, https://github.com/lfit/releng-python-one-password/issues
Project-URL: Download, https://github.com/lfit/releng-python-one-password/tags
Project-URL: Changelog, https://gerrit.linuxfoundation.org/infra/q/project:releng/python-one-password
Platform: any
Classifier: Development Status :: 4 - Beta
Classifier: Programming Language :: Python
License-File: LICENSE.txt
Requires-Dist: typer[all] (~=0.7.0)
Requires-Dist: importlib-metadata ; python_version < "3.8"
Provides-Extra: testing
Requires-Dist: setuptools ; extra == 'testing'
Requires-Dist: pytest ; extra == 'testing'
Requires-Dist: pytest-cov ; extra == 'testing'
